greenclock/__init__.py
greenclock/utils.py
greenclock/version.py
greenclock-0.3.2.dist-info/LICENSE.txt
greenclock-0.3.2.dist-info/METADATA
greenclock-0.3.2.dist-info/WHEEL
greenclock-0.3.2.dist-info/top_level.txt
greenclock-0.3.2.dist-info/RECORD
