Metadata-Version: 2.1
Name: greenclock
Version: 0.3.2
Summary: A library that provides time-based task scheduling using green threads via gevent.
Home-page: https://github.com/pcdinh/greenclock
Author: Pham Cong Dinh
Author-email: pcdinh@gmail.com
License: MIT
Download-URL: https://github.com/pcdinh/greenclock/tarball/0.3.2
Keywords: cron,scheduling,schedule,periodic,jobs,clockwork,gevent
Platform: UNKNOWN
Classifier: Development Status :: 2 - Pre-Alpha
Classifier: Intended Audience :: Developers
Classifier: License :: OSI Approved :: MIT License
Classifier: Programming Language :: Python :: 3.7
Classifier: Programming Language :: Python :: 3.8
Classifier: Natural Language :: English
Classifier: Topic :: Software Development :: Libraries :: Python Modules
Requires-Dist: gevent (>=1.4.0)
